{
    "": "亚洲",
    "hero_title": "约会游戏",
    "hero_subtitle": "哪种约会应用软件能赢得全世界的心？",
    "timestamp": "2016年2月12日",
    "topic_link": "",
    "topic_label": "",
    "section_1_intro_paragraph_bold": "数以百万计的人们利用约会应用软件克服社会障碍、繁忙日常生活和羞怯情绪找到“意中人”。",
    "section_1_intro_paragraph": "很多人发现约会应用软件很有帮助，但也有人失望，还有些极端个案称受到威胁和敲诈。",
    "section_1_map_title": "2015年在50个国家中最受欢迎的约会应用程序",
    "section_1_map_alt": "图示2015年各国下载次数最多的约会应用软件",
    "section_1_paragraph_map": "根据数据分析公司AppAnnie向BBC独家提供的数据，或许讲述了这一现象背后各应用程序的故事。\n\n2015年应用程序市场全球前50名中，两个应用程序占据霸主地位：Badoo和Tinder。\n\nBadoo在推出近10年后，已经在21个国家成为头号约会应用软件。\n\nTinder在18个国家中成为最多人下载的约会应用软件，在很多国家中受欢迎程度仅次于Badoo。",
    "app_popularity_chart_bar_label_1": "Badoo",
    "app_popularity_chart_bar_value_1": "21",
    "app_popularity_chart_bar_label_2": "Tinder",
    "app_popularity_chart_bar_value_2": "18",
    "app_popularity_chart_bar_label_3": "其他",
    "app_popularity_chart_bar_value_3": "11",
    "section_2_subtitle": "欧洲",
    "section_2_map_image_path_480": "",
    "section_2_map_image_path_624": "",
    "section_2_map_alt": "",
    "section_2_paragraph_map": "",
    "section_2_blockquote": "",
    "section_2_blockquote_credit": "",
    "section_2_paragraph_quote": "",
    "section_2_video_title": "",
    "section_2_video_subtitle": "",
    "section_2_paragraph_video": "",
    "section_2_summary": "",
    "section_3_subtitle": "亚洲",
    "section_3_map_image_path_480": "",
    "section_3_map_image_path_624": "",
    "section_3_map_alt": "",
    "section_3_paragraph_map": "",
    "section_3_blockquote": "",
    "section_3_blockquote_credit": "",
    "section_3_paragraph_quote": "",
    "section_3_paragraph_video": "",
    "section_3_video_title": "",
    "section_3_video_subtitle": "",
    "section_3_summary": "",
    "section_4_subtitle": "中东",
    "section_4_map_image_path_480": "",
    "section_4_map_image_path_624": "",
    "section_4_map_alt": "",
    "section_4_paragraph_map": "",
    "section_4_blockquote": "",
    "section_4_blockquote_credit": "",
    "section_4_paragraph_quote": "",
    "section_4_paragraph_video": "",
    "section_4_summary": "",
    "section_5_subtitle": "南美",
    "section_5_map_image_path_480": "",
    "section_5_map_image_path_624": "",
    "section_5_map_alt": "",
    "section_5_paragraph_map": "",
    "section_5_blockquote": "",
    "section_5_blockquote_credit": "",
    "section_5_paragraph_quote": "",
    "section_5_video_title": "",
    "section_5_video_subtitle": "",
    "section_5_paragraph_video": "",
    "section_5_summary": "",
    "section_6_subtitle": "非洲",
    "section_6_map_image_path_480": "",
    "section_6_map_image_path_624": "",
    "section_6_map_alt": "",
    "section_6_paragraph_map": "",
    "section_6_blockquote": "",
    "section_6_blockquote_credit": "",
    "section_6_paragraph_quote": "",
    "section_6_paragraph_video": "",
    "section_6_summary": "",
    "section_7_subtitle": "北美",
    "section_7_map_image_path_480": "",
    "section_7_map_image_path_624": "",
    "section_7_map_alt": "",
    "section_7_paragraph_map": "",
    "section_7_blockquote": "",
    "section_7_blockquote_credit": "",
    "section_7_paragraph_quote": "",
    "section_7_video_title": "",
    "section_7_video_subtitle": "",
    "section_7_paragraph_video": "",
    "section_7_summary": "",
    "section_ws_video_title": "",
    "section_ws_video_subtitle": "",
    "section_ws_paragraph_video": "",
    "section_ws_vpid_video": "",
    "table_heading_country": "",
    "table_heading_top_dating_app": "",
    "browser_notify": "",
    "idt_page_title": "",
    "idt_meta_description": "",
    "credits_title": "",
    "credits": "",
    "onward_journey_title": "",
    "onward_journey_text_1": "",
    "onward_journey_link_1": "",
    "onward_journey_text_2": "",
    "onward_journey_link_2": "",
    "onward_journey_text_3": "",
    "onward_journey_link_3": "",
    "share_this_story": "",
    "about_sharing": "",
    "about_sharing_link": "",
    "share_url": "",
    "full_url": "",
    "share_title": "",
    "share_description": "",
    "twitter_message": "",
    "share_image_url": "http://www.stage.bbc.co.uk/news/special/2016/newsspec_13329/content/english/img/9_promos/facebook.png",
    "badoo": "Badoo",
    "frim": "Frim",
    "heartbeep": "Heartbeep",
    "ipair_meet_your_match": "iPair",
    "lovoo": "Lovoo",
    "momo": "陌陌",
    "paktor": "Paktor（拍拖）",
    "tinder": "Tinder",
    "whoshere": "WhosHere",
    "yyc": "YYC",
    "argentina": "阿根廷",
    "australia": "澳大利亚",
    "austria": "奥地利",
    "belgium": "比利时",
    "brazil": "巴西",
    "bulgaria": "保加利亚",
    "canada": "加拿大",
    "chile": "智利",
    "china": "中国",
    "colombia": "哥伦比亚",
    "czech_republic": "捷克共和国",
    "denmark": "丹麦",
    "egypt": "埃及",
    "finland": "芬兰",
    "france": "法国",
    "germany": "德国",
    "greece": "希腊",
    "hungary": "匈牙利",
    "india": "印度",
    "indonesia": "印度尼西亚",
    "ireland": "爱尔兰",
    "israel": "以色列",
    "italy": "意大利",
    "japan": "日本",
    "kenya": "肯尼亚",
    "kuwait": "科威特",
    "malaysia": "马来西亚",
    "mexico": "墨西哥",
    "netherlands": "荷兰",
    "new_zealand": "新西兰",
    "nigeria": "尼日利亚",
    "norway": "挪威",
    "philippines": "菲律宾",
    "poland": "波兰",
    "portugal": "葡萄牙",
    "romania": "罗马尼亚",
    "russia": "俄罗斯联邦",
    "saudi_arabia": "沙特阿拉伯",
    "singapore": "新加坡",
    "south_africa": "南非",
    "south_korea": "韩国",
    "spain": "西班牙",
    "sweden": "瑞典",
    "switzerland": "瑞士",
    "taiwan": "台湾",
    "thailand": "泰国",
    "turkey": "土耳其",
    "uae": "阿联酋",
    "uk": "英国",
    "ukraine": "乌克兰",
    "usa": "美国",
    "vietnam": "越南"
}